{"id":"b11fe2ce906e25b5","source_id_to_path":{"0":"lib/forge-std/src/Base.sol","1":"lib/forge-std/src/Script.sol","2":"lib/forge-std/src/StdChains.sol","3":"lib/forge-std/src/StdCheats.sol","4":"lib/forge-std/src/StdConstants.sol","5":"lib/forge-std/src/StdJson.sol","6":"lib/forge-std/src/StdMath.sol","7":"lib/forge-std/src/StdStorage.sol","8":"lib/forge-std/src/StdStyle.sol","9":"lib/forge-std/src/StdUtils.sol","10":"lib/forge-std/src/Vm.sol","11":"lib/forge-std/src/console.sol","12":"lib/forge-std/src/console2.sol","13":"lib/forge-std/src/interfaces/IERC20.sol","14":"lib/forge-std/src/interfaces/IMulticall3.sol","15":"lib/forge-std/src/safeconsole.sol","16":"script/Counter.s.sol","17":"script/DeployFastWithdrawalLP.s.sol","18":"script/DeployGoodLend.s.sol","19":"script/DeployGoodStable.s.sol","20":"script/DeployGoodStocks.s.sol","21":"script/DeployGoodSwap.s.sol","22":"script/DeployLiFiBridgeAggregator.s.sol","23":"script/DeployMultiChainBridge.s.sol","24":"script/DeploySwapPriceOracle.s.sol","25":"script/RedeployUBIAndLiFi.s.sol","26":"script/SeedGoodStocks.s.sol","27":"script/TestRegistry.s.sol","28":"src/Counter.sol","29":"src/GoodDollarToken.sol","30":"src/TestRegistry.sol","31":"src/UBIFeeSplitter.sol","32":"src/bridge/FastWithdrawalLP.sol","33":"src/bridge/MultiChainBridge.sol","34":"src/hooks/UBIFeeHook.sol","35":"src/interfaces/IGoodDollarToken.sol","36":"src/lending/DebtToken.sol","37":"src/lending/GoodLendPool.sol","38":"src/lending/GoodLendToken.sol","39":"src/lending/InterestRateModel.sol","40":"src/lending/SimplePriceOracle.sol","41":"src/oracle/SwapPriceOracle.sol","42":"src/stable/CollateralRegistry.sol","43":"src/stable/PegStabilityModule.sol","44":"src/stable/StabilityPool.sol","45":"src/stable/VaultManager.sol","46":"src/stable/gUSD.sol","47":"src/stable/interfaces/IGoodStable.sol","48":"src/stocks/CollateralVault.sol","49":"src/stocks/PriceOracle.sol","50":"src/stocks/SyntheticAsset.sol","51":"src/stocks/SyntheticAssetFactory.sol","52":"src/swap/GoodSwapRouter.sol","53":"src/swap/LiFiBridgeAggregator.sol"},"language":"Solidity"}